resttest3/__init__.py
resttest3/binding.py
resttest3/constants.py
resttest3/contenthandling.py
resttest3/exception.py
resttest3/generators.py
resttest3/runner.py
resttest3/testcase.py
resttest3/utils.py
resttest3/validators.py
resttest3/ext/__init__.py
resttest3/ext/extractor_jmespath.py
resttest3/ext/validator_jsonschema.py
resttest3/reports/__init__.py
resttest3/reports/templite.py
resttest3/reports/template/report_template.html
resttest3-1.0.4.dist-info/LICENSE
resttest3-1.0.4.dist-info/LICENSE.txt
resttest3-1.0.4.dist-info/METADATA
resttest3-1.0.4.dist-info/WHEEL
resttest3-1.0.4.dist-info/entry_points.txt
resttest3-1.0.4.dist-info/top_level.txt
resttest3-1.0.4.dist-info/RECORD
