Metadata-Version: 2.1
Name: resttest3
Version: 1.0.4
Summary: Python RESTful API Testing & Micro benchmarking Tool
Home-page: https://github.com/abhijo89-to/resttest3
Author: Abhilash Joseph C
Author-email: abhilash@softlinkweb.com
License: Apache License, Version 2.0
Keywords: rest,web,http,testing,api
Platform: UNKNOWN
Classifier: Environment :: Console
Classifier: License :: OSI Approved :: Apache Software License
Classifier: Natural Language :: English
Classifier: Programming Language :: Python :: 3.5
Classifier: Programming Language :: Python :: 3.6
Classifier: Programming Language :: Python :: 3.7
Classifier: Programming Language :: Python :: 3.8
Classifier: Programming Language :: Python :: 3.9
Classifier: Topic :: Software Development :: Testing
Classifier: Topic :: Software Development :: Quality Assurance
Classifier: Topic :: Utilities
Requires-Python: >=3.5
Requires-Dist: alive-progress (==1.6.1)
Requires-Dist: pyyaml (==5.3.1)
Requires-Dist: pycurl (==7.43.0.6)
Requires-Dist: jsonpath (==0.82)
Requires-Dist: jmespath (==0.10.0)
Requires-Dist: jsonschema (==3.2.0)
Requires-Dist: certifi (>=2020.11.8)
